LICENSE
MANIFEST.in
README
setup.py
django_pluto.egg-info/PKG-INFO
django_pluto.egg-info/SOURCES.txt
django_pluto.egg-info/dependency_links.txt
django_pluto.egg-info/top_level.txt
pluto/__init__.py
pluto/admin.py
pluto/feeds.py
pluto/models.py