Metadata-Version: 1.0
Name: django-pluto
Version: 0.1
Summary: Pluto aims to provide an architecture to manually import 
Home-page: http://bitbucket.org/activestate/django-pluto/
Author: Michael Gruenewald, ActiveState Software Inc.
Author-email: UNKNOWN
License: MIT
Download-URL: http://bitbucket.org/activestate/django-pluto/downloads/
Platform: UNKNOWN
Classifier: Development Status :: 4 - Beta
Classifier: Framework :: Django
Classifier: Intended Audience :: Developers
Classifier: License :: OSI Approved :: MIT License
Classifier: Operating System :: OS Independent
Classifier: Programming Language :: Python
Classifier: Topic :: Internet :: WWW/HTTP
